{"blog":{"search-4":{"title":"Search Posts"},"archives-3":{"title":"Archives","count":1,"dropdown":0},"adifier_posts_list-3":{"title":"Recent Adverts","number":"5","advert_ids":"","cat_ids":"","orderby":"date","order":"DESC","loc_ids":""}},"single-blog":{"nav_menu-3":{"title":"Quick Links","nav_menu":146},"adifier_posts_list-4":{"title":"Popular Ads","number":"5","advert_ids":"","cat_ids":"","loc_ids":"","orderby":"views","order":"DESC"},"adifier_advert_locations-2":{"title":"Locations","number":"5","cat_ids":""}},"bottom-1":{"media_image-3":{"attachment_id":544,"url":"http:\/\/demo.spoonthemes.net\/themes\/adifier\/wp-content\/uploads\/2018\/03\/logo-footer.png","title":"","size":"full","width":170,"height":50,"caption":"","alt":"","link_type":"custom","link_url":"","image_classes":"","link_classes":"","link_rel":"","link_target_blank":false,"image_title":""},"text-2":{"title":"","text":"Nemo enim ipsam voluptatem quia voluptas sit aspernatur aut odit aut fugit, sed quia consequuntur magni dolores eos qui ratione voluptatem sequi nesciunt consectetur, adipisci velit.\r\n\r\nIf you wish to contact us:\r\n<ul>\r\n \t<li><i class=\"aficon-map-marker-alt-o\" style=\"margin-right: 10px;\"><\/i><span style=\"color: #fff;\">711 Nulla St. Mankato Mississippi 96522<\/span><\/li>\r\n \t<li><i class=\"aficon-phone\" style=\"margin-right: 10px;\"><\/i> <span style=\"color: #fff;\">+(11) 761 89 63<\/font><\/li>\r\n<\/ul>","filter":true,"visual":true}},"bottom-2":{"nav_menu-2":{"title":"Quick Links","nav_menu":146},"search-3":{"title":""}},"bottom-3":{"adifier_posts_list-2":{"title":"Popular Ads","number":"3","advert_ids":"","cat_ids":"","orderby":"views","order":"DESC"}},"custom-sidebar-1":{"adifier_search-2":{"title":"Search Ads"},"adifier_advert_categories-2":{"title":"Categories","number":"9","icon":"yes","cat_ids":""},"adifier_advert_locations-3":{"title":"Locations","number":"7","loc_ids":""}}}